LICENSE
MANIFEST.in
README.rst
pyproject.toml
setup.cfg
setup.py
django_vite_react.egg-info/PKG-INFO
django_vite_react.egg-info/SOURCES.txt
django_vite_react.egg-info/dependency_links.txt
django_vite_react.egg-info/requires.txt
django_vite_react.egg-info/top_level.txt
react/__init__.py
react/admin.py
react/apps.py
react/generic.py
react/mixins.py
react/models.py
react/tests.py
react/views.py
react/components/app.jsx
react/migrations/__init__.py
react/templates/react/react.html
react/templates/react/react_props.html
react/templatetags/react_tags.py
react/templatetags/__pycache__/react_tags.cpython-310.pyc